xboard/__init__.py
xboard/main.py
xboard-1.0.3.dist-info/LICENSE
xboard-1.0.3.dist-info/METADATA
xboard-1.0.3.dist-info/WHEEL
xboard-1.0.3.dist-info/top_level.txt
xboard-1.0.3.dist-info/RECORD
