Metadata-Version: 2.1
Name: xboard
Version: 1.0.3
Summary: API for the XBoard hangboard
Home-page: https://github.com/CossartSim/XBoard
Author: UNKNOWN
Author-email: UNKNOWN
License: UNKNOWN
Platform: UNKNOWN
Requires-Dist: sseclient (>=0.0.20)
